pidp_tools/__init__.py
pidp_tools/analysis.py
pidp_tools/formatting.py
pidp_tools/pid.py
pidp_tools/visualization.py
pidp_tools-1.1.1.dist-info/METADATA
pidp_tools-1.1.1.dist-info/WHEEL
pidp_tools-1.1.1.dist-info/licenses/LICENSE
pidp_tools-1.1.1.dist-info/RECORD
