Metadata-Version: 2.4
Name: pidp_tools
Version: 1.1.1
Summary: A collection of visualization and analysis tools for particle identification
Project-URL: Homepage, https://https://github.com/duberii/pidp_tools
Project-URL: Issues, https://https://github.com/duberii/pidp_tools/issues
Author-email: Richard Dube <richardddube@gmail.com>
License-File: LICENSE
Classifier: Framework :: Jupyter
Classifier: License :: OSI Approved :: MIT License
Classifier: Operating System :: POSIX :: Linux
Classifier: Programming Language :: Python :: 3
Requires-Python: >=3.11
Requires-Dist: ipywidgets>=7.7
Requires-Dist: joblib>=1.4
Requires-Dist: matplotlib>=3.10
Requires-Dist: numpy>=1.26
Requires-Dist: pandas>=2.2
Requires-Dist: pillow>=11
Requires-Dist: plotly>=5.24
Requires-Dist: scikit-learn>=1.6
